{
  "m_GameObject": {
    "m_FileID": 0,
    "m_PathID": 0
  },
  "m_Enabled": 1,
  "m_Script": {
    "m_FileID": 0,
    "m_PathID": 8302033850027404168
  },
  "m_Name": "Fullbody_Hero_Black_Rabbit_SkeletonData",
  "atlasAssets": [
    {
      "m_FileID": 0,
      "m_PathID": -9028359256862364807
    }
  ],
  "scale": 0.005,
  "skeletonJSON": {
    "m_FileID": 0,
    "m_PathID": -3953488442102312214
  },
  "skeletonDataModifiers": [],
  "fromAnimation": [],
  "toAnimation": [],
  "duration": [],
  "defaultMix": 0.2,
  "controller": {
    "m_FileID": 0,
    "m_PathID": 0
  }
}