{
  "m_GameObject": {
    "m_FileID": 0,
    "m_PathID": 0
  },
  "m_Enabled": 1,
  "m_Script": {
    "m_FileID": 0,
    "m_PathID": 8302033850027404168
  },
  "m_Name": "SD_Monster_DreamlessKnight_Life_SkeletonData",
  "atlasAssets": [
    {
      "m_FileID": 0,
      "m_PathID": 6635830836298838566
    }
  ],
  "scale": 0.01,
  "skeletonJSON": {
    "m_FileID": 0,
    "m_PathID": 9126390364277016335
  },
  "skeletonDataModifiers": [],
  "fromAnimation": [],
  "toAnimation": [],
  "duration": [],
  "defaultMix": 0.2,
  "controller": {
    "m_FileID": 0,
    "m_PathID": 0
  }
}